LICENSE
MANIFEST.in
README.md
setup.py
tests/test_basic.py
tests/test_broker.py
tests/test_endpoint.py
tests/test_event.py
tests/test_example.py
tests/test_exchange.py
tests/test_factory.py
tests/test_heartbeat.py
tests/test_protocol.py
tests/test_queue.py
tests/test_testing.py
tests/test_testlib.py
tests/test_tx.py
tests/testlib.py
txAMQP3.egg-info/PKG-INFO
txAMQP3.egg-info/SOURCES.txt
txAMQP3.egg-info/dependency_links.txt
txAMQP3.egg-info/requires.txt
txAMQP3.egg-info/top_level.txt
txamqp/__init__.py
txamqp/client.py
txamqp/codec.py
txamqp/connection.py
txamqp/content.py
txamqp/delegate.py
txamqp/endpoint.py
txamqp/factory.py
txamqp/message.py
txamqp/protocol.py
txamqp/queue.py
txamqp/spec.py
txamqp/testing.py
txamqp/xmlutil.py
txamqp/contrib/__init__.py
txamqp/contrib/thrift/__init__.py
txamqp/contrib/thrift/client.py
txamqp/contrib/thrift/protocol.py
txamqp/contrib/thrift/service.py
txamqp/contrib/thrift/transport.py
txamqp/specs/qpid/amqp.0-8.xml
txamqp/specs/qpid/amqp.0-9.xml
txamqp/specs/qpid/cluster.0-8.xml
txamqp/specs/qpid/cluster.0-9.xml
txamqp/specs/rabbitmq/amqp0-8.stripped.rabbitmq.xml
txamqp/specs/standard/amqp0-8.stripped.xml
txamqp/specs/standard/amqp0-9-1.stripped.xml
txamqp/specs/standard/amqp0-9.stripped.xml